{"categories":[{"category":"Blog, CMS","software":"WordPress","version":""},{"category":"E-commerce, CMS","software":"WooCommerce","version":"3.7.3"},{"category":"Issue Tracker, CMS","software":"BugHerd","version":""},{"category":"Programming Language","software":"PHP","version":""},{"category":"Database","software":"MySQL","version":""},{"category":"CDN","software":"Cloudflare","version":""},{"category":"CDN","software":"cdnjs","version":""},{"category":"Web Server","software":"Nginx","version":""}],"cms":[{"checked_pages":"2","cms":"WooCommerce"}],"original_domain":"wascoskylights.com"}